echo_client/__init__.py
echo_client/__main__.py
echo_client/config.py
echo_client/message.py
echo_client-0.2.2.dist-info/METADATA
echo_client-0.2.2.dist-info/WHEEL
echo_client-0.2.2.dist-info/entry_points.txt
echo_client-0.2.2.dist-info/RECORD
