Metadata-Version: 2.1
Name: echo-client
Version: 0.2.2
Summary: 
Author: Rickyxrc
Author-email: rickyxrc@outlook.com
Requires-Python: >=3.9,<4
Classifier: Programming Language :: Python :: 3
Classifier: Programming Language :: Python :: 3.9
Classifier: Programming Language :: Python :: 3.10
Classifier: Programming Language :: Python :: 3.11
Classifier: Programming Language :: Python :: 3.12
Requires-Dist: prompt-toolkit (>=3.0.43,<4.0.0)
Requires-Dist: pypinyin (>=0.50.0,<0.51.0)
Requires-Dist: pyyaml (>=6.0.1,<7.0.0)
Requires-Dist: rich (>=13.7.0,<14.0.0)
Requires-Dist: websockets (>=12.0,<13.0)
